AUTHORS
MANIFEST.in
Makefile
README.rst
requirements.txt
setup.py
bin/pyprotoc
docs/Makefile
docs/make.bat
docs/source/conf.py
docs/source/index.rst
docs/source/topics/extending.rst
docs/source/topics/languages.rst
docs/source/topics/languages/go.rst
docs/source/topics/languages/javascript-closure.rst
docs/source/topics/languages/javascript-externs.rst
docs/source/topics/languages/protorpc.rst
pyprotobuf/__init__.py
pyprotobuf/codegenerator.py
pyprotobuf/commentresolver.py
pyprotobuf/compiler.py
pyprotobuf/compiler_test.py
pyprotobuf/compilerpass.py
pyprotobuf/dependencysorter.py
pyprotobuf/extensionsresolver.py
pyprotobuf/filepackager.py
pyprotobuf/log.py
pyprotobuf/main.py
pyprotobuf/nameresolver.py
pyprotobuf/nodes.py
pyprotobuf/optionresolver.py
pyprotobuf/outputbuffer.py
pyprotobuf/parser.py
pyprotobuf/parser_test.py
pyprotobuf/tokenizer.py
pyprotobuf/visitor.py
pyprotobuf.egg-info/PKG-INFO
pyprotobuf.egg-info/SOURCES.txt
pyprotobuf.egg-info/dependency_links.txt
pyprotobuf.egg-info/entry_points.txt
pyprotobuf.egg-info/top_level.txt
pyprotobuf/generators/__init__.py
pyprotobuf/generators/closurelib.py
pyprotobuf/generators/externs.py
pyprotobuf/generators/externs_test.py
pyprotobuf/generators/go.py
pyprotobuf/generators/go_test.py
pyprotobuf/generators/protorpc.py
pyprotobuf/generators/protorpc_test.py
pyprotobuf/proto/google/protobuf/descriptor.proto
pyprotobuf/proto/protorpc/message_types.proto
pyprotobuf/testdata/defaults.proto
pyprotobuf/testdata/defaults.proto.py
pyprotobuf/testdata/enum.proto
pyprotobuf/testdata/enum.proto.py
pyprotobuf/testdata/enum_global.proto
pyprotobuf/testdata/enum_global.proto.py
pyprotobuf/testdata/python_custom_field_types.proto
pyprotobuf/testdata/python_custom_field_types.proto.py
pyprotobuf/testdata/simple.proto
pyprotobuf/testdata/simple.proto.py
pyprotobuf/tests/__init__.py
pyprotobuf/tests/a.proto
pyprotobuf/tests/b.proto
pyprotobuf/tests/meta.proto
pyprotobuf/tests/metaproto.proto
pyprotobuf/tests/test.proto