Metadata-Version: 1.0
Name: pyprotobuf
Version: 0.8
Summary: Python protocol buffers compiler
Home-page: http://code.google.com/p/pyprotobuf
Author: Nate Skulic
Author-email: nate.skulic@gmail.com
License: UNKNOWN
Platform: UNKNOWN
